README.rst
setup.py
logrotated/__init__.py
logrotated/dictconfig.py
logrotated/logger.py
logrotated/logrotated.py
logrotated/six.py
logrotated/utils.py
logrotated.egg-info/PKG-INFO
logrotated.egg-info/SOURCES.txt
logrotated.egg-info/dependency_links.txt
logrotated.egg-info/entry_points.txt
logrotated.egg-info/requires.txt
logrotated.egg-info/top_level.txt
logrotated/resources/logrotate
logrotated/tests/__init__.py
logrotated/tests/test_logrotated.py