Metadata-Version: 1.0
Name: logrotated
Version: 0.0.3
Summary: A logrotate human friendly interface.
Home-page: https://github.com/nir0s/logrotated
Author: nir0s
Author-email: nir36g@gmail.com
License: LICENSE
Platform: All
